vialin/__init__.py
vialin-0.0.2.dist-info/LICENSE
vialin-0.0.2.dist-info/METADATA
vialin-0.0.2.dist-info/WHEEL
vialin-0.0.2.dist-info/top_level.txt
vialin-0.0.2.dist-info/RECORD
