Metadata-Version: 2.1
Name: vialin
Version: 0.0.2
Summary: Port c++ to python easily!
Author: Schkimansky
Author-email: <ahmadchawla1432@gmail.com>
Keywords: c++,python,python c++,port,porter,bind,binder,binding,bind c++
Classifier: Development Status :: 1 - Planning
Classifier: Intended Audience :: Developers
Classifier: Programming Language :: Python :: 3
Classifier: Operating System :: Unix
Classifier: Operating System :: MacOS :: MacOS X
Classifier: Operating System :: Microsoft :: Windows
License-File: LICENSE
